{
  "common": {
    "carbon_negative": "Koolstof negatief",
    "carbon_negative_goal": {
      "title": "Ons koolstof negatieve doel",
      "description": "De servers die we gastheer zijn, worden volledig aangedreven door groene, hernieuwbare energie. We werken samen met bedrijven die ons bomen laten planten voor elke service die we organiseren, waardoor extra CO2 van de atmosfeer effectief wordt verwijderd."
    },
    "carbon_stats": {
      "trees_planted": "Bomen Geplant",
      "co2_offset": "CO2 Offset",
      "reforested_land": "Acres van herbiedt land",
      "since_november_2024": "Sinds november 2024",
      "kg_of_co2": "Kg CO2"
    },
    "landing_description": "Pixel Services biedt betaalbare game-hosting met krachtige servers met Ryzen, Intel en EPYC CPU's. Onze plannen omvatten sterke DDoS -bescherming, dagelijkse back -ups en snel netwerken, allemaal gemakkelijk te beheerd via een intuïtief dashboard. Ervaar premium hostingfuncties tegen een budgetvriendelijke prijs en ondersteunt onze toewijding aan duurzaamheid.",
    "explore_plans": "Verken plannen",
    "navigation": {
      "home": "Thuis",
      "services": "Diensten",
      "pricing": "Prijzen",
      "about": "Over",
      "contact": "Contact",
      "faq": "FAQ",
      "support": "Ondersteuning"
    },
    "actions": {
      "login": "Login",
      "register": "Registreer",
      "submit": "indienen",
      "confirm": "Bevestig",
      "cancel": "Annuleren",
      "save": "Opslaan",
      "delete": "Verwijder",
      "edit": "Werk Bij",
      "back": "Terug",
      "next": "Volgende",
      "send": "Verzenden"
    },
    "loading": "Laden...",
    "error": "Fout",
    "success": "Success",
    "welcome": "Welkom",
    "manage": "Beheren",
    "join_discord": "Doe mee met Discord",
    "scroll_down": "Scroll Naar Beneden..."
  },
  "services": {
    "description": "Ontdek ons ​​assortiment hoogwaardige hostingservices die zijn ontworpen om aan uw behoeften te voldoen. Van spelservers tot webhosting, we hebben u gedekt.",
    "list": {
      "minecraft": "Minecraft Server",
      "terraria": "Terraria Server",
      "discord": "Discord Bot",
      "ark": "ARK Server"
    }
  },
  "dashboard": {
    "overview": "Overzicht",
    "recent_emails": "Recente Emails",
    "recent_emails_not_found": "Geen recent emails Gevonden.",
    "services": {
      "title": "Jouw Diensten",
      "description": "Een lijst met uw huidige diensten en hun status.",
      "order_new": "Bestel nieuwe dienst",
      "active_services": "Active Diensten",
      "active_services_description": "Totaal actieve diensten."
    },
    "settings": {
      "title": "Instellingen",
      "save_all": "Sla Alles Op",
      "avatar": {
        "title": "avatar",
        "upload": "Upload",
        "upload_description": "Klik op de avatar om een ​​nieuwe te uploaden."
      },
      "general_information": {
        "username": "Gebruikersnaam",
        "email": "Email",
        "first_name": "Voornaam",
        "last_name": "Achternaam"
      },
      "reset_password": {
        "title": "Wachtwoord Resetten",
        "description": "We zullen u een email sturen met een link om uw wachtwoord te resetten."
      }
    },
    "affiliates": {
      "title": "Jouw Verwantschappen",
      "not_eligible": "U komt nog niet in aanmerking.",
      "request": "Verzoek Verwantschap",
      "modal": {
        "title": "Verzoek Verwantschap",
        "description": "Vertel ons waarom.",
        "placeholder": "Vertel ons alstublieft waarom u een verwantschap wilt hebben.",
        "footer": "Voeg nuttige links toe, vertel ons over uzelf. U wordt op de hoogte gebracht wanneer uw aanvraagstatus is bijgewerkt."
      }
    },
    "balance": {
      "title": "Saldo",
      "description": "Bekijk uw huidige saldo en vul uw account bij.",
      "top_up": "Vul bij",
      "modal": {
        "title": "Vul uw balans aan.",
        "amount_specification": "Bedrag dat u aan uw saldo wilt toevoegen:",
        "footer": "Het bedrag zal onmiddellijk worden toegevoegd aan uw saldo na een succesvolle betaling.",
        "continue_to_payment": "Verder naar betaling."
      }
    },
    "tickets": {
      "title": "Ondersteuning tickets",
      "description": "Krijg hulp van ons support team.",
      "search_label": "Zoeken naar tickets...",
      "showing_tickets": "Er worden {{ticketsLength}} van totaal {{totalItems}} tickets getoond",
      "type_reply": "Schrijf uw reactie...",
      "assigned_to": "Toegewezen aan",
      "filters": {
        "all": "Alle Tickets",
        "open": "Open Tickets",
        "closed": "Gesloten Tickets"
      },
      "priority": {
        "low": "Laag",
        "medium": "Medium",
        "high": "Hoog",
        "urgent": "Dringend"
      },
      "status": {
        "open": "Open",
        "closed": "Gesloten",
        "open_tickets": "Open Tickets",
        "closed_tickets": "Gesloten Tickets"
      },
      "modal": {
        "title": "creëer Ondersteuning Ticket",
        "description": "Beschrijf uw probleem en wij helpen u het op te lossen.",
        "subject": "Onderwerp",
        "message": "Bericht",
        "tips": [
          "Wees specifiek over wat u aan de hand heeft.",
          "Voeg eventuele foutmeldingen toe die u hebt ontvangen",
          "Vermeld welke stappen je al hebt geprobeerd",
          "Vermeld GEEN persoonlijke gegevens! (Hiervoor zullen wij nooit vragen.)",
          "Wees geduldig, Wij helpen u zo snel mogelijk"
        ],
        "create_button": "Creëer Ticket"
      },
      "actions": {
        "close": "Sluit Ticket",
        "reopen": "Heropen Ticket",
        "new": "Nieuw Ticket"
      }
    },
    "billing": {
      "title": "facturatie",
      "invoices": "Facturen",
      "invoices_description": "Totaal aantal facturen."
    },
    "service": {
      "pterodactyl": {
        "overview": "Overzicht",
        "files": "Bestanden",
        "properties": "Eigenschappen",
        "databases": "Databanken",
        "schedules": "Schema's",
        "backups": "Back-ups",
        "console": {
          "type_a_command": "Schrijf een commando...",
          "clear": "Leegmaken"
        },
        "actions": {
          "start": "Start",
          "stop": "Stop",
          "restart": "Herstart",
          "kill": "Nooduitschakeling",
          "backup": "Back-Up",
          "restore": "Herstel",
          "delete": "Verwijder"
        },
        "metrics": {
          "status_label": "Status",
          "status": {
            "online": "Online",
            "offline": "Gestopt",
            "starting": "Starten",
            "stopping": "Stoppen",
            "restarting": "Herstarten",
            "killing": "Nooduitschakelen"
          },
          "cpu": "CPU Gebruik",
          "memory": "Geheugen Gebruik",
          "disk": "Opslag Gebruik",
          "network": "Netwerk",
          "uptime": "Tijd Online"
        }
      }
    },
    "profile": "Profiel",
    "logout": "Log Uit",
    "admin_panel": "Admin Panneel"
  },
  "auth": {
    "email": "Email",
    "password": "Wachtwoord",
    "confirm_password": "Bevestig Wachtwoord",
    "forgot_password": "Wachtwoord Vergeten?",
    "reset_password": "Herstel Wachtwoord",
    "verify_email": "Verifiëer Email",
    "verification_code": "Verificatie Code",
    "first_name": "Voornaam",
    "last_name": "Achternaam",
    "username": "Gebruikersnaam",
    "already_have_account": "Heeft u al een account?",
    "dont_have_account": "Nog geen account?"
  },
  "errors": {
    "page_not_found": "Pagina niet gevonden",
    "unauthorized": "Ongeautoriseerd",
    "server_error": "Server Fout",
    "invalid_credentials": "Onjuiste Gegevens",
    "required_field": "Dit veld is verplicht",
    "password_mismatch": "Wachtwoorden komen niet overeen",
    "invalid_email": "Onjuist Email Adres",
    "generic_error": "Er is iets fout gegaan"
  }
}